justin/__init__.py
justin/justin.py
justin/resources/__init__.py
justin/resources/docker/.dockerignore
justin/resources/docker/Dockerfile
justin/resources/docker/flavors/ci/flavor.toml
justin/resources/docker/flavors/ci/install/ci-scripts/ci-copy-artifacts
justin/resources/docker/flavors/ci/install/entrypoint
justin/resources/docker/flavors/ci/install/install.sh
justin/resources/docker/flavors/minimal/flavor.toml
justin/resources/docker/flavors/minimal/install/entrypoint
justin/resources/docker/flavors/minimal/install/install.sh
justin_runner-0.1.0.dist-info/LICENSE
justin_runner-0.1.0.dist-info/METADATA
justin_runner-0.1.0.dist-info/WHEEL
justin_runner-0.1.0.dist-info/entry_points.txt
justin_runner-0.1.0.dist-info/RECORD
