Metadata-Version: 2.1
Name: justin-runner
Version: 0.1.0
Summary: Runner for 'just' commands inside a container
Home-page: https://git.goral.net.pl/gws/justin.git/about
License: GPL-3.0-only
Keywords: just
Author: Michal Goral
Author-email: dev@goral.net.pl
Requires-Python: >=3.8,<4.0
Classifier: Development Status :: 4 - Beta
Classifier: Environment :: Console
Classifier: Intended Audience :: Developers
Classifier: Intended Audience :: End Users/Desktop
Classifier: Intended Audience :: Information Technology
Classifier: License :: OSI Approved :: GNU General Public License v3 (GPLv3)
Classifier: License :: OSI Approved :: GNU General Public License v3 or later (GPLv3+)
Classifier: Natural Language :: English
Classifier: Operating System :: POSIX
Classifier: Programming Language :: Python :: 3
Classifier: Programming Language :: Python :: 3.8
Classifier: Programming Language :: Python :: 3.9
Classifier: Programming Language :: Python :: 3.10
Classifier: Programming Language :: Python :: 3.11
Classifier: Topic :: Software Development :: Build Tools
Classifier: Topic :: Utilities
Requires-Dist: click (>=8.1,<9.0)
Project-URL: Documentation, https://git.goral.net.pl/gws/justin.git/about
Project-URL: Repository, https://git.goral.net.pl/gws/justin.git
